{
  "menu_title": "自訂難度",
  "unsaved": "未儲存的變更",
  "footer_controls": "WASD/方向鍵：移動  |  左/右：調整  |  Q/E 或 Tab：分類  |  R：預設  |  Enter：確認  |  Esc/F8：關閉",
  "label_default": "預設",
  "label_experimental": "實驗性",
  "label_experimental_short": "EXP",
  "label_status": "狀態",
  "experimental_note": "使用啟發式偵測或保留給未來 hook。儲存是安全的，但效果可能因敵人、Boss 或場景而異。",
  "supported_note": "此版本已支援。",
  "enabled": "開啟",
  "disabled": "關閉",
  "preset_ready": "就緒",
  "preset_note_custom": "手動",
  "action_save_short": "儲存",
  "action_reset_short": "全部重設",
  "action_discard_short": "放棄",
  "action_close_short": "關閉",
  "language_auto": "自動",
  "ai_created_suffix": "（AI 建立）",

  "category_player": "玩家",
  "category_damage": "傷害",
  "category_enemies": "敵人",
  "category_bosses": "Boss",
  "category_drops": "掉落",
  "category_economy": "經濟",
  "category_movement": "移動",
  "category_presets": "預設",
  "category_system": "系統",
  "category_summary": "摘要",
  "category_favorites": "收藏",
  "category_mutators": "變異器",
  "category_boss_profiles": "Boss 設定檔",
  "category_context": "情境",
  "category_adaptive": "自適應",
  "category_search": "搜尋",

  "damage": "基礎傷害",
  "health": "基礎生命",
  "drop_rate": "掉落率",
  "damage_taken": "受到傷害",
  "healing_multiplier": "治療倍率",
  "healing_cost_multiplier": "治療消耗",
  "invincibility_time_multiplier": "無敵時間",
  "skill_damage_multiplier": "技能傷害",
  "silk_spear_damage_multiplier": "絲矛傷害",
  "boss_damage_multiplier": "對 Boss 傷害",
  "common_enemy_damage_multiplier": "對敵人傷害",
  "critical_chance": "暴擊率",
  "critical_damage_multiplier": "暴擊傷害",
  "environmental_damage_multiplier": "環境傷害",
  "boss_damage_taken_multiplier": "來自 Boss 的傷害",
  "common_enemy_damage_taken_multiplier": "來自敵人的傷害",
  "enemy_health_multiplier": "敵人生命",
  "enemy_damage_multiplier": "敵人傷害",
  "enemy_speed_multiplier": "敵人速度",
  "enemy_attack_cooldown_multiplier": "敵人攻擊冷卻",
  "enemy_aggression_multiplier": "敵人攻擊性",
  "boss_health_multiplier": "Boss 生命",
  "boss_speed_multiplier": "Boss 速度",
  "boss_attack_cooldown_multiplier": "Boss 攻擊冷卻",
  "boss_brutal_mode": "Boss 殘酷模式",
  "disable_healing_during_boss": "Boss 戰禁用治療",
  "healing_during_boss_multiplier": "Boss 戰治療",
  "currency_drop_multiplier": "貨幣掉落",
  "item_drop_multiplier": "物品掉落",
  "shop_price_multiplier": "商店價格",
  "boss_reward_multiplier": "Boss 獎勵",
  "death_currency_loss_multiplier": "死亡貨幣損失",
  "player_speed_multiplier": "Hornet 速度",
  "jump_height_multiplier": "跳躍高度",
  "dash_cooldown_multiplier": "衝刺冷卻",
  "ability_cost_multiplier": "能力消耗",
  "silk_cost_multiplier": "絲線消耗",
  "one_hit_mode": "一擊模式",
  "menu_language": "選單語言",

  "apply": "套用",
  "reset": "重設為預設",
  "discard": "放棄變更",
  "back": "關閉選單",
  "preset_easy": "簡單",
  "preset_normal": "普通",
  "preset_hard": "困難",
  "preset_nightmare": "夢魘",
  "preset_one_hit": "一擊",
  "preset_farm": "刷取模式",
  "preset_custom": "自訂",

  "footer_controls_21": "WASD/方向鍵：移動  |  左/右：調整  |  Q/E 或 Tab：分類  |  F：收藏  |  /：搜尋  |  R：預設  |  Enter：確認  |  Esc/F8：關閉",
  "search_label": "搜尋",
  "clear_search": "清除",
  "favorites_short": "收藏",
  "label_supported_short": "OK",
  "label_reserved_short": "預留",
  "label_unsupported_short": "否",
  "reserved_note": "預留：會安全儲存到設定和預設中，但此版本沒有啟用 gameplay hook。",
  "unsupported_note": "此版本不支援。",
  "info": "資訊",
  "description": "說明",
  "comparison_current": "目前",
  "comparison_default": "預設",
  "comparison_difference": "差異",
  "comparison_range": "範圍",
  "run_action": "執行",
  "none": "無",
  "favorite_hint_on": "已收藏。按 F 移除。",
  "favorite_hint_off": "按 F 將此選項加入收藏。",

  "summary_rating": "難度評級",
  "summary_score": "難度分數",
  "summary_profile": "設定檔風格",
  "summary_mutator_count": "啟用的變異器",
  "summary_player_health": "玩家生命",
  "summary_damage_taken": "受到傷害",
  "summary_hornet_damage": "Hornet 傷害",
  "summary_bosses": "Boss",
  "summary_enemies": "敵人",
  "summary_economy": "經濟",
  "summary_healing": "治療",
  "summary_drops": "掉落",
  "summary_mutators": "變異器",
  "summary_generous": "更慷慨",
  "summary_strict": "更嚴格",
  "summary_normal": "普通",
  "summary_blocked": "已阻止",
  "summary_reduced": "已降低",
  "summary_much_harder": "困難很多",
  "summary_slightly_harder": "稍微更難",
  "summary_easier": "更簡單",
  "summary_farm": "刷取",
  "summary_custom": "自訂",
  "rating_very_easy": "非常簡單",
  "rating_easy": "簡單",
  "rating_normal": "普通",
  "rating_hard": "困難",
  "rating_extreme": "極限",
  "rating_chaotic": "混亂",

  "mutator_one_hit": "一擊",
  "mutator_no_healing": "無治療",
  "mutator_low_gravity": "低重力",
  "mutator_double_damage": "雙倍傷害",
  "mutator_glass_cannon": "玻璃大砲",
  "mutator_fast_enemies": "快速敵人",
  "mutator_tank_enemies": "坦克敵人",
  "mutator_aggressive_enemies": "激進敵人",
  "mutator_randomized_enemy_health": "隨機敵人生命",
  "mutator_rich_world": "富饒世界",
  "mutator_poor_world": "貧瘠世界",
  "mutator_expensive_shops": "昂貴商店",
  "mutator_no_death_loss": "死亡無損失",
  "mutator_boss_frenzy": "Boss 狂暴",
  "mutator_no_mercy": "毫不留情",
  "mutator_extended_fights": "延長戰鬥",

  "saved_preset_selector": "已儲存預設",
  "create_preset": "建立預設",
  "save_preset": "儲存目前",
  "load_preset": "載入所選",
  "duplicate_preset": "複製所選",
  "rename_preset": "重新命名所選",
  "delete_preset": "刪除所選",
  "reset_preset_file": "重設預設檔",
  "export_preset": "匯出目前",
  "import_preset": "匯入最新",
  "reload_presets": "重新載入列表",
  "preset_name_input": "預設名稱",
  "preset_folder": "預設資料夾",
  "import_folder": "匯入資料夾",
  "export_folder": "匯出資料夾",
  "last_message": "最後訊息",
  "reset_category": "重設分類",
  "boss_profiles_enabled": "啟用 Boss 設定檔",
  "boss_profiles_fallback_global": "使用全域 Boss 設定",
  "boss_profiles_file": "Boss 設定檔",
  "boss_profiles_path": "Boss 設定檔路徑",
  "context_boss_rules": "Boss 戰規則",
  "context_exploration_rules": "探索規則",
  "context_low_health_rule": "低生命規則",
  "context_death_streak_tracking": "連續死亡記錄",
  "adaptive_enabled": "自適應難度",
  "adaptive_boss_assist": "自適應 Boss 輔助",
  "adaptive_exploration_assist": "自適應探索輔助",
  "adaptive_economy_assist": "自適應經濟輔助",
  "adaptive_max_assist": "最大輔助",
  "adaptive_apply_mode": "自適應套用模式",
  "adaptive_mode_suggest": "僅建議",
  "adaptive_mode_confirm": "先確認",
  "adaptive_mode_auto": "自動套用"
}
